ppcls
