Metadata-Version: 1.0
Name: ppcls-notebook
Version: 0.1.1.7
Summary: PaddleClas for notebook
Home-page: https://github.com/PaddlePaddle/PaddleClas
Author: tianzhi
Author-email: ylj_yanglijuan@163.com
License: UNKNOWN
Platform: UNKNOWN
